RawGithubURL-0.1.2.dist-info/METADATA
RawGithubURL-0.1.2.dist-info/RECORD
RawGithubURL-0.1.2.dist-info/WHEEL
RawGithubURL-0.1.2.dist-info/entry_points.txt
RawGithubURL-0.1.2.dist-info/top_level.txt
github/__about__.py
github/__init__.py
github/github.py
