Metadata-Version: 2.1
Name: RawGithubURL
Version: 0.1.2
Summary: RawGithubURL基于Python实现，用于获取GitHub资源文件的真实访问地址，同时支持自动转换Markdown文档中相对路径的资源引用，以便外网访问
Home-page: https://github.com/zhuifengshen/RawGithubURL
Author: Devin
Author-email: 1324556701@qq.com
License: MIT
Keywords: gitHub,resource,real URL,raw url
Platform: UNKNOWN
Classifier: Programming Language :: Python :: 2
Classifier: Programming Language :: Python :: 3
Classifier: License :: OSI Approved :: MIT License
Classifier: Operating System :: OS Independent
Requires-Python: >=2.7, <4
